mj_brutal/__init__.py
mj_brutal/santa.py
mj_brutal-0.0.1.dist-info/METADATA
mj_brutal-0.0.1.dist-info/WHEEL
mj_brutal-0.0.1.dist-info/top_level.txt
mj_brutal-0.0.1.dist-info/RECORD
