Metadata-Version: 2.1
Name: mj-brutal
Version: 0.0.1
Summary: we are so brutal
Home-page: UNKNOWN
Author: brutal
License: UNKNOWN
Platform: UNKNOWN
